q2_thapbi_pict/__init__.py
q2_thapbi_pict/_prepare_reads_sample_tally.py
q2_thapbi_pict/citations.bib
q2_thapbi_pict/plugin_setup.py
q2_thapbi_pict-0.0.1.dist-info/LICENSE.rst
q2_thapbi_pict-0.0.1.dist-info/METADATA
q2_thapbi_pict-0.0.1.dist-info/WHEEL
q2_thapbi_pict-0.0.1.dist-info/entry_points.txt
q2_thapbi_pict-0.0.1.dist-info/top_level.txt
q2_thapbi_pict-0.0.1.dist-info/RECORD
