Metadata-Version: 2.1
Name: q2_thapbi_pict
Version: 0.0.1
Summary: Qiime2 plugin for THAPBI PICT.
Home-page: https://github.com/peterjc/q2-thapbi-pict
Download-URL: https://github.com/peterjc/q2-thapbi-pict
Author: Peter Cock
Author-email: peter.cock@hutton.ac.uk
Project-URL: Documentation, https://thapbi-pict.readthedocs.io/
Project-URL: Source, https://github.com/peterjc/q2-thapbi-pict/
Project-URL: Tracker, https://github.com/peterjc/q2-thapbi-pict/issues
Classifier: Development Status :: 4 - Beta
Classifier: Environment :: Console
Classifier: Intended Audience :: Science/Research
Classifier: License :: Freely Distributable
Classifier: License :: OSI Approved :: MIT License
Classifier: Natural Language :: English
Classifier: Operating System :: MacOS :: MacOS X
Classifier: Operating System :: POSIX :: Linux
Classifier: Programming Language :: Python
Classifier: Programming Language :: Python :: 3
Classifier: Topic :: Scientific/Engineering
Classifier: Topic :: Scientific/Engineering :: Bio-Informatics
Requires-Python: >=3.7
License-File: LICENSE.rst
Requires-Dist: thapbi-pict <1.1,>=1.0.12
Requires-Dist: q2-types >=2023.5
Requires-Dist: q2cli >=2023.5
Requires-Dist: biom-format >=2.1.12
